pepperize_projen_awscdk_app_ts/__init__.py
pepperize_projen_awscdk_app_ts/py.typed
pepperize_projen_awscdk_app_ts/_jsii/__init__.py
pepperize_projen_awscdk_app_ts/_jsii/projen-awscdk-app-ts@0.0.790.jsii.tgz
pepperize_projen_awscdk_app_ts-0.0.790.dist-info/LICENSE
pepperize_projen_awscdk_app_ts-0.0.790.dist-info/METADATA
pepperize_projen_awscdk_app_ts-0.0.790.dist-info/WHEEL
pepperize_projen_awscdk_app_ts-0.0.790.dist-info/top_level.txt
pepperize_projen_awscdk_app_ts-0.0.790.dist-info/RECORD
